hb9imsutils/__init__.py
hb9imsutils/test.py
hb9imsutils/units.py
hb9imsutils-0.2.12.dist-info/licenses/LICENSE
hb9imsutils-0.2.12.dist-info/METADATA
hb9imsutils-0.2.12.dist-info/WHEEL
hb9imsutils-0.2.12.dist-info/top_level.txt
hb9imsutils-0.2.12.dist-info/RECORD
