Metadata-Version: 2.4
Name: hb9imsutils
Version: 0.2.12
Summary: A collection of handwritten utilities
Home-page: https://github.com/HB9IMS/imsutils.git
Author: Patrik Roth (HB9IMS)
Author-email: patrik.roth@gmx.net
License: BSD-3-Clause
Classifier: Programming Language :: Python :: 3
Classifier: License :: OSI Approved :: BSD License
Classifier: Operating System :: OS Independent
Requires-Python: >=3.7
License-File: LICENSE
Dynamic: license-file
